ipfshttpclient4ipwb/__init__.py
ipfshttpclient4ipwb/encoding.py
ipfshttpclient4ipwb/exceptions.py
ipfshttpclient4ipwb/filescanner.py
ipfshttpclient4ipwb/http.py
ipfshttpclient4ipwb/multipart.py
ipfshttpclient4ipwb/requests_wrapper.py
ipfshttpclient4ipwb/utils.py
ipfshttpclient4ipwb/version.py
ipfshttpclient4ipwb/client/__init__.py
ipfshttpclient4ipwb/client/base.py
ipfshttpclient4ipwb/client/bitswap.py
ipfshttpclient4ipwb/client/block.py
ipfshttpclient4ipwb/client/bootstrap.py
ipfshttpclient4ipwb/client/config.py
ipfshttpclient4ipwb/client/dht.py
ipfshttpclient4ipwb/client/files.py
ipfshttpclient4ipwb/client/key.py
ipfshttpclient4ipwb/client/miscellaneous.py
ipfshttpclient4ipwb/client/name.py
ipfshttpclient4ipwb/client/object.py
ipfshttpclient4ipwb/client/pin.py
ipfshttpclient4ipwb/client/pubsub.py
ipfshttpclient4ipwb/client/repo.py
ipfshttpclient4ipwb/client/swarm.py
ipfshttpclient4ipwb/client/unstable.py
ipfshttpclient4ipwb-0.6.0.dist-info/LICENSE
ipfshttpclient4ipwb-0.6.0.dist-info/WHEEL
ipfshttpclient4ipwb-0.6.0.dist-info/METADATA
ipfshttpclient4ipwb-0.6.0.dist-info/RECORD
