Metadata-Version: 2.1
Name: ipfshttpclient4ipwb
Version: 0.6.0
Summary: Python IPFS HTTP CLIENT library
Home-page: https://ipfs.io/ipns/12D3KooWEqnTdgqHnkkwarSrJjeMP2ZJiADWLYADaNvUb6SQNyPF/
License: MIT License
Keywords: ipfs storage distribution development
Author: py-ipfs-http-client team
Author-email: 
Requires-Python: >=3.7
Classifier: Development Status :: 3 - Alpha
Classifier: Intended Audience :: Developers
Classifier: Intended Audience :: Information Technology
Classifier: Intended Audience :: Science/Research
Classifier: Topic :: Internet
Classifier: Topic :: Scientific/Engineering
Classifier: Topic :: System :: Filesystems
Classifier: Topic :: System :: Networking
Classifier: License :: OSI Approved :: MIT License
Classifier: Programming Language :: Python :: 3 :: Only
Classifier: Programming Language :: Python :: 3.7
Classifier: Programming Language :: Python :: 3.8
Requires-Dist: multiaddr (>=0.0.7)
Requires-Dist: requests (>=2.11)
Project-URL: Documentation, https://ipfs.io/ipns/12D3KooWEqnTdgqHnkkwarSrJjeMP2ZJiADWLYADaNvUb6SQNyPF/docs/
